dwai/__init__.py
dwai/dwai.py
dwai/unified_llm.py
dwai/azure/__init__.py
dwai/azure/completions.py
dwai/azure/devtools_testutils/__init__.py
dwai/azure/devtools_testutils/azure_recorded_testcase.py
dwai/azure/model_api/__init__.py
dwai/azure/model_api/base_completions.py
dwai/azure/model_api/completions.py
dwai/azure/test/__init__.py
dwai/azure/test/conftest.py
dwai/azure/test/test_chat_completions.py
dwai/azure/test/test_chat_completions_async.py
dwai/azure/test/test_completions.py
dwai/azure/test/test_completions_async.py
dwai/azure/test/test_dall_e.py
dwai/azure/test/test_dall_e_async.py
dwai/azure/test/test_embeddings.py
dwai/azure/test/test_embeddings_async.py
dwai/bailian/__init__.py
dwai/bailian/model_api/__init__.py
dwai/bailian/model_api/base_completions.py
dwai/bailian/model_api/completions.py
dwai/bailian/model_api/exceptions.py
dwai/bailian/model_api/models.py
dwai/core/__init__.py
dwai/core/base_completions.py
dwai/core/exceptions.py
dwai/fangzhou/__init__.py
dwai/fangzhou/model_api/__init__.py
dwai/fangzhou/model_api/completions.py
dwai/llm/__init__.py
dwai/llm/azure.py
dwai/llm/bl.py
dwai/llm/dw.py
dwai/llm/fangzhou.py
dwai/llm/minimax.py
dwai/llm/pangu.py
dwai/llm/tx.py
dwai/llm/wenxin.py
dwai/llm/zhipu.py
dwai/mini/__init__.py
dwai/mini/completions.py
dwai/mini/model_api/__init__.py
dwai/mini/model_api/base_completions.py
dwai/mini/model_api/completions.py
dwai/pangu/__init__.py
dwai/pangu/model_api/__init__.py
dwai/pangu/model_api/base_completions.py
dwai/pangu/model_api/completions.py
dwai/pangu/model_api/message.py
dwai/pangu/model_api/models.py
dwai/tione/__init__.py
dwai/tione/completions.py
dwai/tione/common/__init__.py
dwai/tione/common/base_completions.py
dwai/tione/common/exception/__init__.py
dwai/tione/common/exception/tencent_cloud_sdk_exception.py
dwai/tione/v20191022/__init__.py
dwai/tione/v20191022/errorcodes.py
dwai/tione/v20191022/models.py
dwai/tione/v20191022/tione_client.py
dwai/tione/v20211111/__init__.py
dwai-0.4.6.dist-info/AUTHORS.rst
dwai-0.4.6.dist-info/LICENSE
dwai-0.4.6.dist-info/METADATA
dwai-0.4.6.dist-info/WHEEL
dwai-0.4.6.dist-info/top_level.txt
dwai-0.4.6.dist-info/RECORD
