Metadata-Version: 2.1
Name: dwai
Version: 0.4.6
Summary: 云商大模型Python SDK
Home-page: https://github.com/tluo-github/dwai
Author: 罗涛
Author-email: luotao@shizhuang-inc.com
License: Apache Software License 2.0
Keywords: dwai
Classifier: Development Status :: 2 - Pre-Alpha
Classifier: Intended Audience :: Developers
Classifier: License :: OSI Approved :: Apache Software License
Classifier: Natural Language :: English
Classifier: Programming Language :: Python :: 3
Classifier: Programming Language :: Python :: 3.6
Classifier: Programming Language :: Python :: 3.7
Classifier: Programming Language :: Python :: 3.8
Requires-Python: >=3.6
License-File: LICENSE
License-File: AUTHORS.rst
Requires-Dist: jsonpath-ng ==1.5.3
Requires-Dist: twine ==4.0.2
Requires-Dist: tencentcloud-sdk-python ==3.0.956
